findsame/__init__.py
findsame/calc.py
findsame/common.py
findsame/config.py
findsame/main.py
findsame/parallel.py
findsame/benchmark/__init__.py
findsame/benchmark/benchmark.py
findsame/benchmark/plot.py
findsame/tests/__init__.py
findsame/tests/test.py
findsame-0.1.2.data/scripts/findsame
findsame-0.1.2.dist-info/LICENSE
findsame-0.1.2.dist-info/METADATA
findsame-0.1.2.dist-info/WHEEL
findsame-0.1.2.dist-info/top_level.txt
findsame-0.1.2.dist-info/RECORD
