Metadata-Version: 2.1
Name: findsame
Version: 0.1.2
Summary: Find duplicate files and directories using hashes and a Merkle tree
Home-page: https://github.com/elcorto/findsame
Author: Steve Schmerler
Author-email: git@elcorto.com
License: BSD 3-Clause
Keywords: merkle-tree hash duplicates multithreading multiprocessing
Platform: UNKNOWN
